starflow/VERSION
starflow/__init__.py
starflow/base_piece.py
starflow/logger.py
starflow/task.py
starflow/task_branch.py
starflow/actions/github_actions.py
starflow/cli/__init__.py
starflow/cli/cli.py
starflow/cli/utils/__init__.py
starflow/cli/utils/config-starflow-local.toml
starflow/cli/utils/constants.py
starflow/cli/utils/docker-compose.yaml
starflow/cli/utils/pieces_repository.py
starflow/cli/utils/platform.py
starflow/client/__init__.py
starflow/client/github_rest_client.py
starflow/client/local_files_client.py
starflow/client/starflow_backend_client.py
starflow/client/legacy/fs_client.py
starflow/client/legacy/s3_client.py
starflow/custom_operators/__init__.py
starflow/custom_operators/docker_operator.py
starflow/custom_operators/k8s_branch_operator.py
starflow/custom_operators/k8s_operator.py
starflow/custom_operators/python_operator.py
starflow/custom_operators/worker_operator.py
starflow/custom_operators/deprecated/base_operator.py
starflow/custom_operators/deprecated/external_python_operator.py
starflow/custom_operators/sidecar/__init__.py
starflow/custom_operators/sidecar/fuse.conf
starflow/custom_operators/sidecar/logger.py
starflow/custom_operators/sidecar/mount.py
starflow/custom_operators/sidecar/rclone.conf
starflow/custom_operators/sidecar/sidecar_lifecycle.sh
starflow/exceptions/__init__.py
starflow/exceptions/exceptions.py
starflow/models/__init__.py
starflow/models/output_modifier.py
starflow/schemas/__init__.py
starflow/schemas/container_resources.py
starflow/schemas/deploy_mode.py
starflow/schemas/display_result.py
starflow/schemas/piece_metadata.py
starflow/schemas/shared_storage.py
starflow/scripts/__init__.py
starflow/scripts/build_docker_images_pieces.py
starflow/scripts/load_piece.py
starflow/scripts/run_piece_branch_docker.py
starflow/scripts/run_piece_docker.py
starflow/scripts/deprecated/create_docker_compose_file.py
starflow/scripts/deprecated/deprecated_piece_dry_run.py
starflow/scripts/deprecated/docker_compose_constants.py
starflow_py-0.59.0.dist-info/LICENSE
starflow_py-0.59.0.dist-info/METADATA
starflow_py-0.59.0.dist-info/WHEEL
starflow_py-0.59.0.dist-info/entry_points.txt
starflow_py-0.59.0.dist-info/top_level.txt
starflow_py-0.59.0.dist-info/RECORD
