Metadata-Version: 2.1
Name: starflow-py
Version: 0.59.0
Summary: Python package for starflow.
Author-email: Alexandre Lazar <alexandre.lazar@gmail.com>
License: 
Project-URL: homepage, https://github.com/prochain-star-atlas/starflow
Project-URL: documentation, https://prochain-star-atlas.github.io/starflow-docs/
Project-URL: repository, https://github.com/prochain-star-atlas/starflow
Keywords: starflow,airflow,gui
Classifier: Development Status :: 4 - Beta
Classifier: Programming Language :: Python :: 3
Classifier: Topic :: Scientific/Engineering
Classifier: Topic :: Software Development :: Libraries :: Python Modules
Classifier: Topic :: Software Development :: User Interfaces
Requires-Python: >=3.8
License-File: LICENSE
Requires-Dist: pydantic >=2.11.0
Requires-Dist: tomli ==2.0.1
Requires-Dist: tomli-w ==1.0.0
Requires-Dist: PyYAML ==6.0.1
Requires-Dist: jsonschema >=4.19.1
Requires-Dist: click ==8.1.3
Requires-Dist: rich >=13.4.2
Requires-Dist: colorama ==0.4.6
Provides-Extra: airflow
Requires-Dist: apache-airflow ==3.0.6 ; extra == 'airflow'
Requires-Dist: apache-airflow-providers-cncf-kubernetes ==10.8.0 ; extra == 'airflow'
Requires-Dist: apache-airflow-providers-docker ==4.4.2 ; extra == 'airflow'
Requires-Dist: python-keycloak ==5.2.0 ; extra == 'airflow'
Provides-Extra: cli
Requires-Dist: urllib3 >=2.3.0 ; extra == 'cli'
Requires-Dist: cryptography >=44.0.0 ; extra == 'cli'
Requires-Dist: pyOpenSSL >=25.0.0 ; extra == 'cli'
Requires-Dist: PyGithub >=2.5.0 ; extra == 'cli'
Requires-Dist: docker >=7.1.0 ; extra == 'cli'
Requires-Dist: kubernetes >=32.0.0 ; extra == 'cli'
Requires-Dist: bottle >=0.13.2 ; extra == 'cli'
Requires-Dist: requests >=2.31.0 ; extra == 'cli'
Requires-Dist: python-keycloak ==5.8.1 ; extra == 'cli'
Provides-Extra: full
Requires-Dist: bottle >=0.13.2 ; extra == 'full'
Requires-Dist: urllib3 >=2.3.0 ; extra == 'full'
Requires-Dist: cryptography >=44.0.0 ; extra == 'full'
Requires-Dist: pyOpenSSL >=25.0.0 ; extra == 'full'
Requires-Dist: PyGithub >=2.5.0 ; extra == 'full'
Requires-Dist: docker >=7.1.0 ; extra == 'full'
Requires-Dist: kubernetes ==33.1.0 ; extra == 'full'
Requires-Dist: apache-airflow ==3.0.6 ; extra == 'full'
Requires-Dist: apache-airflow-providers-cncf-kubernetes ==10.8.0 ; extra == 'full'
Requires-Dist: apache-airflow-providers-docker ==4.4.2 ; extra == 'full'
Requires-Dist: python-keycloak ==5.8.1 ; extra == 'full'
